[
  {
    "key": "game/finalroute.rpy_L192_0",
    "original": "Slave? That’s awful!",
    "context": "https://github.com/ponytranz/FwBCN/blob/main/game/finalroute.rpy#L192"
  },
  {
    "key": "game/finalroute.rpy_L192_1",
    "original": "I’m glad I could have helped, my Queen.",
    "context": "https://github.com/ponytranz/FwBCN/blob/main/game/finalroute.rpy#L192"
  },
  {
    "key": "game/finalroute.rpy_L230_0",
    "original": "Would you like to save?",
    "context": "https://github.com/ponytranz/FwBCN/blob/main/game/finalroute.rpy#L230"
  },
  {
    "key": "game/finalroute.rpy_L241_0",
    "original": "Of course, your majesty…",
    "context": "https://github.com/ponytranz/FwBCN/blob/main/game/finalroute.rpy#L241"
  },
  {
    "key": "game/finalroute.rpy_L241_1",
    "original": "No way! I refuse!",
    "context": "https://github.com/ponytranz/FwBCN/blob/main/game/finalroute.rpy#L241"
  },
  {
    "key": "game/finalroute.rpy_L292_0",
    "original": "I’ll never join you!",
    "context": "https://github.com/ponytranz/FwBCN/blob/main/game/finalroute.rpy#L292"
  },
  {
    "key": "game/finalroute.rpy_L292_1",
    "original": "A harem? Alright, I’ll join you…",
    "context": "https://github.com/ponytranz/FwBCN/blob/main/game/finalroute.rpy#L292"
  },
  {
    "key": "game/finalroute.rpy_L377_0",
    "original": "Inventory",
    "context": "https://github.com/ponytranz/FwBCN/blob/main/game/finalroute.rpy#L377"
  },
  {
    "key": "game/finalroute.rpy_L377_1",
    "original": "Moxie's Satchel",
    "context": "https://github.com/ponytranz/FwBCN/blob/main/game/finalroute.rpy#L377"
  },
  {
    "key": "game/finalroute.rpy_L377_2",
    "original": "[chocolates] Chocolates",
    "context": "https://github.com/ponytranz/FwBCN/blob/main/game/finalroute.rpy#L377"
  },
  {
    "key": "game/finalroute.rpy_L377_3",
    "original": "[roses] Roses",
    "context": "https://github.com/ponytranz/FwBCN/blob/main/game/finalroute.rpy#L377"
  },
  {
    "key": "game/finalroute.rpy_L377_4",
    "original": "City Permit",
    "context": "https://github.com/ponytranz/FwBCN/blob/main/game/finalroute.rpy#L377"
  },
  {
    "key": "game/finalroute.rpy_L377_5",
    "original": "Hooks and Ropes",
    "context": "https://github.com/ponytranz/FwBCN/blob/main/game/finalroute.rpy#L377"
  },
  {
    "key": "game/finalroute.rpy_L377_6",
    "original": "Leather Armor",
    "context": "https://github.com/ponytranz/FwBCN/blob/main/game/finalroute.rpy#L377"
  },
  {
    "key": "game/finalroute.rpy_L377_7",
    "original": "Scimitar",
    "context": "https://github.com/ponytranz/FwBCN/blob/main/game/finalroute.rpy#L377"
  },
  {
    "key": "game/finalroute.rpy_L408_0",
    "original": "Should I return to the real world? (Crystal Ball)",
    "context": "https://github.com/ponytranz/FwBCN/blob/main/game/finalroute.rpy#L408"
  }
]